trussit/__init__.py
trussit/main.py
trussit/repogen/repomaker.pyc
trussit/repogen/solvers.pyc
trussit-1.4.dist-info/LICENSE
trussit-1.4.dist-info/METADATA
trussit-1.4.dist-info/WHEEL
trussit-1.4.dist-info/entry_points.txt
trussit-1.4.dist-info/top_level.txt
trussit-1.4.dist-info/RECORD
